mwx/__init__.py
mwx-1.6.dist-info/LICENSE.txt
mwx-1.6.dist-info/METADATA
mwx-1.6.dist-info/WHEEL
mwx-1.6.dist-info/top_level.txt
mwx-1.6.dist-info/RECORD
